MANIFEST.in
setup.py
flask_rst.egg-info/PKG-INFO
flask_rst.egg-info/SOURCES.txt
flask_rst.egg-info/dependency_links.txt
flask_rst.egg-info/entry_points.txt
flask_rst.egg-info/not-zip-safe
flask_rst.egg-info/requires.txt
flask_rst.egg-info/top_level.txt
flaskrst/__init__.py
flaskrst/cli.py
flaskrst/helpers.py
flaskrst/parsers.py
flaskrst/modules/__init__.py
flaskrst/modules/archive.py
flaskrst/modules/blog.py
flaskrst/modules/page.py
flaskrst/modules/pygments.py
flaskrst/modules/tags.py
flaskrst/static/style.css
flaskrst/templates/archive_index.html
flaskrst/templates/archive_month.html
flaskrst/templates/archive_year.html
flaskrst/templates/blog_index.html
flaskrst/templates/blog_post.html
flaskrst/templates/layout.html
flaskrst/templates/page_show.html
flaskrst/templates/tags_cloud.html
flaskrst/templates/tags_inside_post.html
flaskrst/templates/tags_taged_with.html