Metadata-Version: 1.0
Name: flask-rst
Version: 0.1
Summary: Create a static website from simple reStructuredText files
Home-page: http://bitbucket.org/Jarus/flask-rstblog
Author: Christoph Heer
Author-email: Christoph.Heer@googlemail.com
License: BSD
Platform: UNKNOWN
Classifier: Development Status :: 4 - Beta
Classifier: Environment :: Web Environment
Classifier: License :: OSI Approved :: BSD License
Classifier: Operating System :: OS Independent
Classifier: Programming Language :: Python
